LICENSE
MANIFEST.in
__main__.py
cookies.txt
mget.conf
setup.cfg
setup.py
/home/mssg3r/Works/MGET-1.4.4/./Mget/utils/CPPMGET/common.cpp
/home/mssg3r/Works/MGET-1.4.4/./Mget/utils/CPPMGET/cpycode.pyx
/home/mssg3r/Works/MGET-1.4.4/./Mget/utils/CPPMGET/main.cpp
Mget/__init__.py
Mget/__main__.py
Mget/mget.py
Mget/downloader/__init__.py
Mget/downloader/client.py
Mget/downloader/common.py
Mget/downloader/http.py
Mget/extractor/__init__.py
Mget/extractor/animebam.py
Mget/extractor/aniupload.py
Mget/extractor/anivids.py
Mget/extractor/auengine.py
Mget/extractor/auengine_io.py
Mget/extractor/byzoo.py
Mget/extractor/common.py
Mget/extractor/ftwcdn.py
Mget/extractor/mp4upload.py
Mget/extractor/play44.py
Mget/extractor/playlist-ext.py
Mget/extractor/playpanda.py
Mget/extractor/trollvid.py
Mget/extractor/veevr.py
Mget/extractor/video44.py
Mget/extractor/videodrive.py
Mget/extractor/videonest.py
Mget/extractor/yourupload.py
Mget/utils/__init__.py
Mget/utils/avconv.py
Mget/utils/common.py
Mget/utils/exception.py
Mget/utils/handlers.py
mget.egg-info/PKG-INFO
mget.egg-info/SOURCES.txt
mget.egg-info/dependency_links.txt
mget.egg-info/entry_points.txt
mget.egg-info/top_level.txt