Metadata-Version: 1.1
Name: mget
Version: 1.4.4
Summary: HTTP file/video downloader
Home-page: UNKNOWN
Author: Ramesh Mani Maran
Author-email: mssg3r@gmail.com
License: UNKNOWN
Keywords: download mget http file downloader video mp4upload
Platform: UNKNOWN
Classifier: Development Status :: 5 - Production/Stable
Classifier: Environment :: Console
Classifier: License :: OSI Approved :: GNU General Public License v2 (GPLv2)
Classifier: Operating System :: POSIX :: Linux
Classifier: Topic :: Internet
Classifier: Programming Language :: Cython
Classifier: Programming Language :: Python :: 3.4
